odoo/addons/account_banking_mandate_sale_contact/README.rst
odoo/addons/account_banking_mandate_sale_contact/__init__.py
odoo/addons/account_banking_mandate_sale_contact/__manifest__.py
odoo/addons/account_banking_mandate_sale_contact/i18n/account_banking_mandate_sale_contact.pot
odoo/addons/account_banking_mandate_sale_contact/i18n/es.po
odoo/addons/account_banking_mandate_sale_contact/i18n/it.po
odoo/addons/account_banking_mandate_sale_contact/models/__init__.py
odoo/addons/account_banking_mandate_sale_contact/models/res_company.py
odoo/addons/account_banking_mandate_sale_contact/models/res_config_settings.py
odoo/addons/account_banking_mandate_sale_contact/models/res_partner.py
odoo/addons/account_banking_mandate_sale_contact/models/sale_order.py
odoo/addons/account_banking_mandate_sale_contact/readme/CONFIGURE.md
odoo/addons/account_banking_mandate_sale_contact/readme/CONTRIBUTORS.md
odoo/addons/account_banking_mandate_sale_contact/readme/DESCRIPTION.md
odoo/addons/account_banking_mandate_sale_contact/readme/USAGE.md
odoo/addons/account_banking_mandate_sale_contact/static/description/icon.png
odoo/addons/account_banking_mandate_sale_contact/static/description/icon.svg
odoo/addons/account_banking_mandate_sale_contact/static/description/index.html
odoo/addons/account_banking_mandate_sale_contact/tests/__init__.py
odoo/addons/account_banking_mandate_sale_contact/tests/test_account_banking_mandate_sale_contact.py
odoo/addons/account_banking_mandate_sale_contact/views/res_config_settings.xml
odoo/addons/account_banking_mandate_sale_contact/views/res_partner.xml
odoo_addon_account_banking_mandate_sale_contact-17.0.1.0.0.5.dist-info/METADATA
odoo_addon_account_banking_mandate_sale_contact-17.0.1.0.0.5.dist-info/WHEEL
odoo_addon_account_banking_mandate_sale_contact-17.0.1.0.0.5.dist-info/top_level.txt
odoo_addon_account_banking_mandate_sale_contact-17.0.1.0.0.5.dist-info/RECORD
