Metadata-Version: 2.1
Name: odoo-addon-account_banking_mandate_sale_contact
Version: 17.0.1.0.0.5
Requires-Python: >=3.10
Requires-Dist: odoo-addon-account_banking_mandate_contact>=17.0dev,<17.1dev
Requires-Dist: odoo-addon-account_banking_mandate_sale>=17.0dev,<17.1dev
Requires-Dist: odoo>=17.0a,<17.1dev
Summary: Add a specific contact mandate to sale orders
Home-page: https://github.com/OCA/bank-payment
License: AGPL-3
Author: =?utf-8?q?Alberto_Mart=C3=ADnez=2C_Odoo_Community_Association_=28OCA=29?=
Author-email: support@odoo-community.org
Classifier: Programming Language :: Python
Classifier: Framework :: Odoo
Classifier: Framework :: Odoo :: 17.0
Classifier: License :: OSI Approved :: GNU Affero General Public License v3
Classifier: Development Status :: 4 - Beta
